book_return_pkg/__init__.py
book_return_pkg/return_calculator.py
book_return_lib-0.0.1.dist-info/LICENSE
book_return_lib-0.0.1.dist-info/METADATA
book_return_lib-0.0.1.dist-info/WHEEL
book_return_lib-0.0.1.dist-info/top_level.txt
book_return_lib-0.0.1.dist-info/RECORD
